{
  "sections": {
    "sc_hero": {
      "type": "sc-hero-banner",
      "settings": {
        "heading": "Nature's First Food for Modern Wellness",
        "subtext": "Sacred Colostrum is nature's most bioactive superfood — packed with growth factors, immunoglobulins, and bioactives for whole-body health.",
        "button_label": "Shop Now",
        "button_url": "/collections/all",
        "bg_color": "#1a1a1a",
        "text_color": "#ffffff",
        "btn_bg": "#ffffff",
        "btn_text": "#111111",
        "min_height": 869,
        "overlay_opacity": 30
      }
    },
    "sc_marquee_1": {
      "type": "sc-marquee",
      "blocks": {
        "item_1": { "type": "item", "settings": { "text": "100% Grass-Fed Colostrum" } },
        "item_2": { "type": "item", "settings": { "text": "Third-Party Tested" } },
        "item_3": { "type": "item", "settings": { "text": "No Fillers or Additives" } },
        "item_4": { "type": "item", "settings": { "text": "60-Day Money Back Guarantee" } },
        "item_5": { "type": "item", "settings": { "text": "New Zealand Sourced" } }
      },
      "block_order": ["item_1","item_2","item_3","item_4","item_5"],
      "settings": {
        "bg_color": "#f5f5f5",
        "text_color": "#111111",
        "separator": "✦",
        "font_size": 14,
        "padding": 16,
        "speed": 30
      }
    },
    "sc_featured_product": {
      "type": "featured-product",
      "settings": {}
    },
    "sc_marquee_2": {
      "type": "sc-marquee",
      "blocks": {
        "item_1": { "type": "item", "settings": { "text": "Supports Immune Function" } },
        "item_2": { "type": "item", "settings": { "text": "Gut Health & Leaky Gut" } },
        "item_3": { "type": "item", "settings": { "text": "Athletic Recovery" } },
        "item_4": { "type": "item", "settings": { "text": "Skin Rejuvenation" } }
      },
      "block_order": ["item_1","item_2","item_3","item_4"],
      "settings": {
        "bg_color": "#111111",
        "text_color": "#ffffff",
        "separator": "✦",
        "font_size": 14,
        "padding": 16,
        "speed": 25
      }
    },
    "sc_benefits": {
      "type": "sc-benefits",
      "blocks": {
        "b1": { "type": "benefit", "settings": { "label": "Immunity", "title": "Immune Support", "text": "Rich in immunoglobulins IgG, IgA, and IgM that help prime and strengthen your immune system." } },
        "b2": { "type": "benefit", "settings": { "label": "Gut", "title": "Gut Barrier Integrity", "text": "Growth factors like IGF-1 help seal and restore the gut lining, reducing leaky gut symptoms." } },
        "b3": { "type": "benefit", "settings": { "label": "Performance", "title": "Athletic Recovery", "text": "Naturally occurring growth factors support muscle repair and reduce recovery time." } },
        "b4": { "type": "benefit", "settings": { "label": "Skin", "title": "Skin & Collagen", "text": "Bioactives stimulate collagen production and cell renewal for a more youthful appearance." } },
        "b5": { "type": "benefit", "settings": { "label": "Energy", "title": "Energy & Vitality", "text": "Supports mitochondrial function and metabolic health for sustained daily energy." } },
        "b6": { "type": "benefit", "settings": { "label": "Longevity", "title": "Longevity Factors", "text": "Lactoferrin and bioactives offer powerful antioxidant and anti-aging properties." } }
      },
      "block_order": ["b1","b2","b3","b4","b5","b6"],
      "settings": {
        "heading": "Why Sacred Colostrum Works",
        "subtext": "Every scoop delivers nature's most complete nutritional matrix — bioactives that work synergistically to transform your health.",
        "button_label": "Learn More",
        "button_url": "/pages/science",
        "bg_color": "#ffffff",
        "heading_color": "#111111",
        "text_color": "#555555",
        "pad_v": 80
      }
    },
    "sc_bioactives": {
      "type": "sc-media-text",
      "blocks": {
        "a1": { "type": "accordion", "settings": { "title": "What bioactives are in colostrum?", "content": "<p>Sacred Colostrum contains over 400 bioactives including IGF-1, TGF-β, lactoferrin, proline-rich polypeptides, and all four immunoglobulin classes.</p>" } },
        "a2": { "type": "accordion", "settings": { "title": "How is it processed?", "content": "<p>We use a gentle low-heat process to preserve the delicate bioactives — never ultra-pasteurized.</p>" } },
        "a3": { "type": "accordion", "settings": { "title": "Is it third-party tested?", "content": "<p>Yes. Every batch is independently tested for potency, purity, and safety before it reaches you.</p>" } },
        "a4": { "type": "accordion", "settings": { "title": "Where is it sourced?", "content": "<p>Our colostrum is ethically sourced from pasture-raised cows in New Zealand — only surplus colostrum collected after calves are fully fed.</p>" } }
      },
      "block_order": ["a1","a2","a3","a4"],
      "settings": {
        "heading": "Nature's Most Complete Nutritional Matrix",
        "button_label": "Explore the Science",
        "button_url": "/pages/science",
        "layout": "right",
        "bg_color": "#f9f7f4",
        "heading_color": "#111111",
        "text_color": "#555555",
        "pad_v": 0,
        "img_radius": 0
      }
    },
    "sc_testimonials": {
      "type": "sc-testimonials",
      "blocks": {
        "r1": { "type": "review", "settings": { "quote": "I have more energy than I've had in years. Sacred Colostrum has become my non-negotiable daily ritual.", "name": "Sarah M.", "subtitle": "Verified Buyer" } },
        "r2": { "type": "review", "settings": { "quote": "My gut issues have improved dramatically after 3 months. I couldn't believe how quickly it worked.", "name": "James K.", "subtitle": "Verified Buyer" } },
        "r3": { "type": "review", "settings": { "quote": "As an athlete, my recovery time has dropped significantly. I feel stronger and less inflamed.", "name": "Priya R.", "subtitle": "Verified Buyer" } },
        "r4": { "type": "review", "settings": { "quote": "The skin benefits alone are worth it. I look years younger and my hair is thicker than ever.", "name": "Michael T.", "subtitle": "Verified Buyer" } }
      },
      "block_order": ["r1","r2","r3","r4"],
      "settings": {
        "heading": "1,000+ lives transformed",
        "button_label": "Read All Reviews",
        "button_url": "/pages/reviews",
        "bg_color": "#ffffff",
        "heading_color": "#111111",
        "text_color": "#444444",
        "pad_v": 80
      }
    },
    "sc_compare": {
      "type": "sc-compare",
      "blocks": {
        "row1": { "type": "row", "settings": { "feature": "100% Grass-Fed & Pasture-Raised", "us": true, "col_b": false, "col_c": false } },
        "row2": { "type": "row", "settings": { "feature": "Third-Party Lab Tested", "us": true, "col_b": true, "col_c": false } },
        "row3": { "type": "row", "settings": { "feature": "No Fillers or Artificial Additives", "us": true, "col_b": false, "col_c": false } },
        "row4": { "type": "row", "settings": { "feature": "Low-Heat Processing (Bioactives Preserved)", "us": true, "col_b": false, "col_c": true } },
        "row5": { "type": "row", "settings": { "feature": "Ethically Sourced (Calves First)", "us": true, "col_b": false, "col_c": false } },
        "row6": { "type": "row", "settings": { "feature": "60-Day Money Back Guarantee", "us": true, "col_b": false, "col_c": false } },
        "row7": { "type": "row", "settings": { "feature": "Bioactive Potency Verified", "us": true, "col_b": true, "col_c": false } }
      },
      "block_order": ["row1","row2","row3","row4","row5","row6","row7"],
      "settings": {
        "heading": "The Sacred Difference",
        "subtext": "Not all colostrum is created equal. Here's why Sacred Colostrum stands apart.",
        "col_us": "Sacred Colostrum",
        "col_b": "Competitor B",
        "col_c": "Competitor C",
        "button_label": "Shop Now",
        "button_url": "/collections/all",
        "bg_color": "#f9f7f4",
        "heading_color": "#111111",
        "text_color": "#555555",
        "highlight_bg": "#111111",
        "highlight_text": "#ffffff",
        "pad_v": 80
      }
    },
    "sc_faq": {
      "type": "sc-faq",
      "blocks": {
        "f1": { "type": "faq", "settings": { "question": "What is bovine colostrum?", "answer": "<p>Bovine colostrum is the first milk produced by cows in the first 24–72 hours after birth. It's packed with growth factors, immunoglobulins, and over 400 bioactives.</p>" } },
        "f2": { "type": "faq", "settings": { "question": "How do I take Sacred Colostrum?", "answer": "<p>Mix one scoop (5g) into water, smoothies, or your favourite beverage daily. For best results, take on an empty stomach in the morning.</p>" } },
        "f3": { "type": "faq", "settings": { "question": "How long before I see results?", "answer": "<p>Many customers notice improved energy and digestion within 2–4 weeks. We recommend at least 3 months of consistent use for full benefits.</p>" } },
        "f4": { "type": "faq", "settings": { "question": "Is it safe for lactose intolerant people?", "answer": "<p>Colostrum contains very low levels of lactose compared to regular milk. Many lactose-sensitive individuals tolerate it well, but we recommend consulting your doctor.</p>" } },
        "f5": { "type": "faq", "settings": { "question": "What is your money-back guarantee?", "answer": "<p>We offer a full 60-day money-back guarantee. If you're not satisfied for any reason, contact us for a complete refund — no questions asked.</p>" } },
        "f6": { "type": "faq", "settings": { "question": "Is colostrum ethical?", "answer": "<p>Yes. We only collect surplus colostrum after calves have been fully fed. Our farmers follow strict animal welfare standards in New Zealand.</p>" } }
      },
      "block_order": ["f1","f2","f3","f4","f5","f6"],
      "settings": {
        "heading": "Frequently Asked Questions",
        "subtext": "Everything you need to know about Sacred Colostrum.",
        "button_label": "Ask Us More",
        "button_url": "/pages/contact",
        "bg_color": "#ffffff",
        "heading_color": "#111111",
        "text_color": "#555555",
        "pad_v": 80
      }
    },
    "sc_cta": {
      "type": "sc-cta-banner",
      "settings": {
        "heading": "Start your wellness journey today",
        "subtext": "Join 1,000+ people who've transformed their health with Sacred Colostrum.",
        "btn1_label": "Shop Now",
        "btn1_url": "/collections/all",
        "btn1_bg": "#ffffff",
        "btn1_text": "#111111",
        "btn2_label": "Learn About the Science",
        "btn2_url": "/pages/science",
        "bg_color": "#111111",
        "text_color": "#ffffff",
        "pad_v": 106,
        "overlay_opacity": 0
      }
    }
  },
  "order": [
    "sc_hero",
    "sc_marquee_1",
    "sc_featured_product",
    "sc_marquee_2",
    "sc_benefits",
    "sc_bioactives",
    "sc_testimonials",
    "sc_compare",
    "sc_faq",
    "sc_cta"
  ]
}
